olscrypto/__init__.py
olscrypto/decryptor.py
olscrypto-0.1.8.dist-info/METADATA
olscrypto-0.1.8.dist-info/WHEEL
olscrypto-0.1.8.dist-info/top_level.txt
olscrypto-0.1.8.dist-info/RECORD
