Metadata-Version: 2.1
Name: olscrypto
Version: 0.1.8
Summary: OLS decrypt library
Author: Highmaru, Inc.
Author-email: dhshin@highmaru.com
Classifier: Development Status :: 1 - Planning
Classifier: Intended Audience :: Developers
Classifier: Programming Language :: Python :: 3
Classifier: Operating System :: Unix
Classifier: Operating System :: MacOS :: MacOS X
Classifier: Operating System :: Microsoft :: Windows
Requires-Dist: pycryptodome >=3.20.0
